<achievements>
    <a best="68" current="3" name="GameWinStreak" time="1757617677895"/>
    <a best="90" current="3" name="MatchWinStreak" time="1754583500036"/>
    <a best="308" name="TotalGameWins" time="1761335503539"/>
    <a best="303" name="TotalMatchWins" time="1761335503539"/>
    <a best="4" name="NeedForSpeed" time="1753212932631"/>
    <a best="-35" name="Overkill" time="1757615366766"/>
    <a best="19" name="LifeToSpare" time="1757540620896"/>
    <a best="1" name="Hellbent" time="1750264058326"/>
    <a best="2" name="ArcaneMaster" time="1753212932632"/>
    <a best="4" name="StormChaser" time="1753388717211"/>
    <a best="2" name="ManaScrewed" time="1755275613809"/>
    <a best="9" name="ManaFlooded" time="1748029429134"/>
    <a best="5" name="RagsToRiches" time="1752093586395"/>
</achievements>
